Workbook

Sheet Programme Profile
B1: Read Me First
A2: Programme Name | B2: Please enter the Name of the Programme (Max 20 words) See the guidance on the approach to the Programme and Project Planning | C2: DRC Species Program
A3: Program Lead | B3: Please enter the Name of the Program Lead
A4: Program Team Member | B4: Please list the name of Program Staff. This will be the list of staff who will have access to the Program information in the new PMEL system.
A5: Program Duration | B5: Please indicate the duration of Program. Minimum Duration of the Program is 5 years. | C5: FROM: | D5: FY2026
C6: TO: | D6: FY2030
A7: Programme Description | B7: Please enter a short description of the Programme (Max 200 words) | C7: Wildlife The DRC Wildlife Program aims to safeguard the country’s iconic species of elephants, bonobos, chimpanzees, and lowland gorillas, while improving community well-being and ecosystem health. Operating in biodiversity-rich yet high-threat landscapes, the program integrates law enforcement support, community-led conservation, conflict mitigation, and zoonotic disease prevention. It promotes sustainable livelihoods and delivers targeted awareness campaigns to shift attitudes towards the sustainable use of wildlife resources. Strengthened institutional collaboration and protected area management further enhance the effectiveness of wildlife protection. To reduce human-elephant conflict, the program applies the Conflicts to Coexistence (C2C) model, empowering Indigenous Peoples and Local Communities (IPLCs) to co-develop solutions that benefit both people and wildlife. Additionally, it positions conservation as a public health priority through interventions that prevent zoonotic spillover in high-risk areas. Cross-border policy advocacy also plays a key role, targeting the illegal timber trade and transboundary wildlife trafficking through regional cooperation. This program is aligned with WWF’s Global Goal of Zero Extinction and directly contributes to the Global Biodiversity Framework (GBF), especially Targets 1, 3, 4, 9, and 21, SDGs 1, 3, 15, and 14, and the Convention on Biological Diversity (CBD).
A8: Program Focus / Focal Area | B8: Please select one or more Conservation and/or Human well being Focus areas that your program will be focusing on. Please make sure this is a subset of what's selected in the OSP.
A9: Geographic Scope (Landscape) | B9: Please list all the operational land/seascapes that are within the scope of the Program. For each land/seascape, provide short description of why the scape is critical in the context of this Program (max 200 words per land/seascape). Example: Name of the land/seascape: Description max 200 words. All land/seascapes must must apply ESSF. Guidance on landscape definition is here | C9: Name of land/seascape | D9: Description (Max 200 words)
C10: Salonga Landscape | D10: The Salonga landscape encompasses one of the largest intact blocks of lowland forest in the Congo Basin and as such, is of exceptional importance for biodiversity, CO2 sequestration and the stabilization of hydrological systems at both regional and global levels. The size and integrity of forest, with its extensive network of river systems provides secure habitat for forest elephants, bonobos, Congo peacocks, bongos, giant pangolins and eight other species of diurnal primates, with high numbers of bird and freshwater fish species as well. At the centre of the landscape and occupying over a third of our area of intervention, is the Salonga National Park (33,676 km2), the largest national park in Africa, and the third largest tropical forest park in the world. The Park is divided into southern (17,323 km2) and northern (16,353 km2) blocks, separated by a corridor approximately 45 km wide. The Park was declared a UNESCO World Heritage Site in 1984, and reclassified as one of the sites in danger in 1999.
C11: Virunga Landscape | D11: Our zone of intervention in the Virunga landscape is located in the province of North Kivu, along the western border of Virunga National Park, the first national park created in Africa, famous for the iconic mountain gorilla and also home to the eastern lowland gorilla and chimpanzee. It is an area of rich faunal biodiversity, with 210 mammalian species, 21 of which are endemic to DRC, and over 700 species of birds, including several endemics. The region lies within the Albertine Rift, has volcanic mountains and rugged terrain with average slopes of greater than 15%. The province itself, an area of 59,483 km2, has a population of approximately 8.9 million inhabitants spread over six territories: Beni, Lubero, Masisi, Nyiragongo, Rutshuru, and Walikale. The agricultural sector is of paramount importance, providing nearly six out of ten jobs. Rural communities depend highly on access to natural resources for their livelihoods, and supplying the demand from urban areas for products including charcoal and bush meat is placing unsustainable pressure on the environment and wildlife.
C12: Lacs Tumba-Mai Ndombe | D12: The Lacs Tumba-Mai Ndombe landscape lies along the western border of the DRC, and includes one of the largest wetlands in the world. In the northern zone, there are varied forest stands including swamp forests on peatland, limbali forests and secondary forests. The wetland ecosystem provides important bird habitat and was designated as a Ramsar Site in 2008. The diverse ecosystems are home to emblematic and endemic species of fauna, including large mammals, reptiles, amphibians and fish. There are also high densities of two threatened species of African apes, chimpanzees (Pan troglodytes) and bonobos (Pan paniscus), as well as forest elephants (Loxodonta cyclotis), hippopotamus (Hippopotamus amphibius), approximately 16 species of diurnal monkeys, seven species of duikers, and leopards. There are four protected areas within the landscape: the Ngiri Triangle Nature Reserve, the Tumba Lediima Reserve, the Eala Botanical Garden and the Mabali Scientific Reserve. The first three are managed by the Institut Congolais pour la Conservation de la Nature (ICCN) and the last by the DRC Ministry of Scientific Research. There are also community forest concessions of which 6, covering 14,900 ha, have been set up with the primary objectives of conservation and bonobo ecotourism (Malebo area, located in the Bateke-Nord chiefdom). The Malebo area contains some of the highest densities of bonobos recorded (0.79 bonobo/km²). The landscape is home to more than two million people, with almost half resident in the city of Mbandaka to the north, and the remainder in smaller towns (Lukolela, Makanza, Bikoro, Bomongo, Inongo, Kwamouth, Bolobo, etc.) and villages situated along the rivers and lakes. Farming, fishing, hunting, and collecting non-timber forest products (NTFPs) are the main sources of income for rural communities.
C13: Itombwe | D13: Itombwe landscape is based in Bukavu, the largest city in the province of South Kivu. Areas of concern to conservation efforts include the Natural Reserve of Itombwe (RNI), located at the western escarpment of the Albertine Rift, at the northern end of Lake Tanganyika. The RNI occupies an area of 5,732 km2 in the Itombwe Massif, which is part of the African Rift Lakes Region, one of the 35 global priority places under the WWF Global Priority Framework (GPF). Flagship species in the region are the lowland gorilla, chimpanzee, and a small population of forest elephants among other protected species in the DRC. The reserve has been identified as a site of significant importance for the conservation of threatened and endemic birds, amphibians, and various endangered large mammals. There are approximately 1,182,000 inhabitants in the province, who are very unevenly distributed: there is a high concentration in the eastern part, along the main roads, shores and low slopes near Lake Tanganyika. This is where the major urban centres such as Luvungi, Sange, Uvira, Nundu, Baraka, are located. The largely rural population is dependent on subsistence agriculture and exploitation of natural resources. There is a high level of insecurity in the region due to armed militia groups
C14: Luki Project Site | D14: The Luki project site centres in and around the Luki Biosphere Reserve (RBL), which was created in 1976, and is recognized by UNESCO. The 33,000 ha reserve is a community protected area in the larger Mayombe forest ecosystem, located in the province of Kongo Central. The presence of the Central African chimpanzee (Pan troglodytes troglodytes) in the Reserve was recently confirmed. The Reserve is the only remaining forested area without significant degradation, as the province is relatively small and densely populated. There are two large cities, Boma and Matadi, and the area is within a day’s travel to Kinshasa. As a result, forests surrounding the reserve have been decimated both by agricultural expansion and harvesting for timber and charcoal production.
A15: Thematic Scope (Practices) | B15: Please list all the thematic that are relevant to the scope of the OSP. (Choice: Finance & Administration, Fundraising, Communications, P&C, Partnership, PMEL, etc.). For each theme, provide short description of why the theme is critical in the context of the OSP (max 200 words per theme). Example: Name of the theme: Description max 200 words. See Guidance by PPMS Step - Element 1.2 | C15: Name of Thematic Scope | D15: Description (Max 200 words)
C16: Wildlife

Sheet Situation Analysis
B1: Read Me First
A2: Political | B2: Please enter the concise analysis (narrative) of context and trends (political, social, economic, climate & environmental, and institutional) in country that has effects on the scope of the Programme. Depending on the nature of the program, some context may be more relevant than the others. (See Guidance by PPMS Step - Element 1.3, and IUCN-CMP Unified classification of Threat 2.0s) | D2: The political situation in the target landscapes reflects a variety of dynamics depending on local realities. In the Virunga region, political complexity remains high due to persistent security tensions. The DRC government has instituted a state of siege in conflict-affected provinces, particularly North Kivu, accompanied by significant security, judicial, administrative and constitutional reforms. The Disarmament, Demobilization, Reintegration and Stabilization Program (PDDRC-S) supports this security dynamic. However, the reform of the Independent National Electoral Commission (CENI) in 2022 has raised concerns about possible electoral tensions. On the other hand, the DRC's active participation in the Nairobi and Luanda peace processes underlines a commitment to long-term stability in the east of the country. In comparison, the Lac Tumba Mai-Ndombé landscape presents a relatively stable and peaceful provincial political context, supported by innovative policies, particularly in terms of peatland and biodiversity preservation. This stability is accompanied by a recent improvement in respect for the rights of indigenous peoples, thanks to the enactment of specific laws reinforcing their protection. Similarly, in the Mayombe Mangroves landscape, the political framework is strengthened by provincial autonomy established by the law on the free administration of the provinces. This autonomy encourages local management in key areas such as the environment, land and energy. WWF plays a key role in working closely with the authorities and stakeholders to ensure effective implementation of environmental policies. Finally, in the Salonga National Park, sustained efforts are being made to strengthen governance and security. Particular emphasis is placed on the application of a robust environmental and social framework, with the overriding aim of preventing human rights abuses and ensuring the sustainable and respectful management of the park's resources.
A3: Social | D3: In the Virunga region, complexity remains high due to persistent insecurity for over 30 years, exacerbated by the activities of rebel groups such as the M23. The provinces of North and South Kivu are experiencing massive internal population displacements, severe food insecurity, and widespread human rights violations, including sexual violence and indiscriminate shelling. This major humanitarian crisis continues to weigh heavily on peace efforts, despite regional initiatives such as the Nairobi and Luanda processes, and government reforms aimed at stabilizing eastern DRC. In contrast, the Lac Tumba Mai-Ndombé landscape displays a diverse and relatively stable social framework, inhabited by a cultural mosaic composed mainly of farmers, hunters, fishermen and gatherers. Although the precise representation of indigenous populations is uncertain, their recent recognition thanks to new legislation bears witness to a positive evolution in the protection of their rights. Large towns such as Inongo and Mbandaka are major socio-economic hubs, with local populations heavily dependent on water resources. The Mayombe Mangrove landscape, on the other hand, presents a mono-ethnic context mainly dominated by ethnic Kongo groups (Yombe, Woyo, Asolongo and Mboma), living in harmony in an urban ano-rural setting. This cultural homogeneity contributes to a stable political environment, facilitated by provincial autonomy established by the law on the free administration of the provinces, which enables effective local management, particularly in the environmental field. Finally, in the Salonga National Park, current efforts are focused on strengthening governance and environmental and social security. Significant action is being taken to prevent human rights abuses and ensure sustainable management of the park's natural resources, despite the challenges posed by the region's isolation and logistical complexity.
A4: Economic | D4: The Virunga region remains marked by chronic instability due to the prolonged presence of rebel groups and the illicit exploitation of its abundant natural resources. The provinces of North and South Kivu are rich in precious minerals such as coltan, gold, cassiterite and wolframite, highly prized resources that fuel a complex clandestine trade involving regional and international players. This illegal trade deprives the Congolese state of substantial revenues, while indirectly financing armed conflict. Violent clashes also lead to massive population displacement, exacerbating a major humanitarian crisis characterized by serious human rights violations. In contrast, the Lac Tumba Mai-Ndombe landscape features a local economy dominated by agriculture and fishing, which are the main sources of income for the communities. Despite the presence of largely inactive industrial logging concessions, artisanal and illegal logging and the growing production of charcoal represent major economic and environmental challenges for this region. In the Mayombe Mangrove landscape, the state remains the main employer, while the local economy is essentially based on agriculture, fishing and small-scale trade. However, the lack of opportunities is driving many young people into unsustainable activities such as illegal logging and charcoal-making, threatening the natural resources of the protected areas. Agricultural products such as cocoa, palm oil, coffee, cassava, bananas and corn are important economic assets. Finally, the Salonga National Park is pursuing its efforts in terms of environmental and social governance to ensure sustainable management, despite significant logistical challenges linked to geographical isolation. Targeted initiatives aim to strengthen the protection of natural resources while guaranteeing respect for human rights.
A5: Climate & Environmental | D5: The Virunga region remains marked by chronic instability, exacerbated by the presence of rebel groups and the illicit exploitation of its abundant natural resources. The provinces of North and South Kivu, rich in strategic minerals such as coltan, gold and cassiterite, suffer the effects of a complex clandestine trade involving regional and international players. This illegal trade directly fuels armed conflict, while depriving the Congolese state of vital financial resources. In addition, the effects of climate change are aggravating the situation, leading to catastrophic flooding, mass displacement and increased pressure on already fragile local communities. This dynamic also contributes to the recruitment of young people into armed groups, fuelling a vicious circle of violence and poverty. By comparison, the Lac Tumba Mai-Ndombé landscape is characterized by a predominantly agricultural and fish-farming economy but is facing increasing pressure on its forest resources. Rapid deforestation, largely due to artisanal logging and charcoal production, threatens the integrity of the vast rainforests and peatlands, essential for climate regulation. The environmental situation is worrying, with deforestation rates well above the national average, jeopardizing the region's unique biodiversity. In the Mayombe Mangrove landscape, the state remains the main employer, but local economic activities remain limited, pushing young people towards unsustainable practices such as charcoal-making and illegal logging. The hot, humid equatorial climate exacerbates environmental vulnerability, and unsustainable agricultural practices and recurrent bush fires threaten forest, savannah and aquatic ecosystems. Finally, in the Salonga National Park, despite its geographical isolation and the associated logistical challenges, initiatives continue to strengthen environmental and social governance to ensure the sustainable protection of its exceptional biodiversity, while ensuring respect for the rights of local populations.
A6: Institutional | D6: The Virunga region continues to face persistent instability, amplified by the presence of armed groups and the illegal exploitation of strategic natural resources. The provinces of North and South Kivu, rich in essential minerals such as coltan, gold and cassiterite, are subject to a complex clandestine trade involving regional and international players, which finances conflicts and impoverishes the Congolese state. The situation is exacerbated by climate change, illustrated by recurrent large-scale flooding such as that which recently occurred in South Kivu province. Faced with these challenges, initiatives such as the Priority Action Plan (PAP 2025) in North Kivu and the Provincial Development Plan (2024-2028) in South Kivu are being implemented with the support of international partners to improve living conditions and strengthen the resilience of local communities. In the Lac Tumba Mai-Ndombe landscape, shared between the Equateur and Mai-Ndombe provinces, the dominant economic activities are agriculture and fishing, which play a key role for local communities. However, artisanal logging and the growing production of charcoal represent significant environmental pressures. A decentralized institutional structure, comprising provincial governments, provincial assemblies and local authorities, collaborates with institutions such as the Institut Congolais pour la Conservation de la Nature (ICCN) to ensure sustainable management of natural resources. The Mayombe Mangrove landscape, located entirely within the province of Kongo Central, benefits from a provincial administration structured around a governor and a provincial assembly. Despite this favorable institutional context, limited economic opportunities are driving young people towards the unsustainable exploitation of natural resources. The State and various stakeholders, notably the ICCN, the Local Steering Committee (CLP) and civil society, are working together to ensure the sustainable management of natural resources. Finally, the Salonga National Park is pursuing its environmental and social protection efforts, despite major logistical and geographical constraints. Targeted initiatives are being deployed to ensure the conservation of biodiversity and the protection of local communities' rights.

Sheet Stakeholder Analysis
B2: Stakeholder Name | C2: Stakeholder Description | D2: Stakeholder Type | E2: Engagement Stage (planning, Implementation, MEL) | F2: Engagement methods & strategies | G2: Due Diligence (Y/N)
A3: READ Me First | B3: Please list key groups of stakeholders (people and organizations) who will be influenced by, have an impact on, or will help implement conservation to engage during the Programme planning, implementation, monitoring, and learning. Max 20 words. See Guidance by PPMS Step - Element 1.4 | C3: Please briefly explain the significance of engaging with the stakeholder, and what you expect from the effective engagement. max 200 words | D3: Please indicate the type of stakeholders (individual or organization): - Indigenous People & Local Communities - Civil Society Organization - Government's / Public Sector Organization - Companies / Private Sector - Universities / Research Organization - Other | E3: Please indicate what stage each stakeholder group will be engaged - Programme planning, implementation, M&E, and Learning, etc. | F3: Please describe how each stakeholder group will be engaged. Make sure that stakeholders will have regular access to the Programme information and, as appropriate, are aware of complaints procedures and feedback mechanisms. | G3: For corporate & philanthropic partners (major donors, trusts, and foundations), please indicate if the due diligence is already conducted or not. For Other stakeholders, put NA. Corporate Partnership Rules & Guidelines Philanthropy Due Diligence
B4: RAPNAV | C4: Network of Associations for the Protection of Nature around Virunga | D4: Network CSO | E4: Designing, Planning, implementation and monitoring | F4: Service Agreement | G4: Yes
B5: PIDP | C5: Integrated Program for the Development of the Pygmy People in Kivu | D5: SHOW JUMPING | E5: Implementation | F5: Service Agreement | G5: Yes
B6: North Kivu Civil Society | C6: Société civile Force Vive du Nord-Kivu | D6: Network CSO | E6: Implementation | F6: MoU. Advocacy | G6: Yes
B7: UGADEC | C7: Union of Conservation Associations Gorillas for Community Development in Eastern DR Congo | D7: Network CSO | E7: Implementation | F7: MoU. Supporting Community forest concessions | G7: Yes
B8: APAB | C8: Batwa Indigenous Peoples Association | D8: SHOW JUMPING | E8: Implementation | F8: MoU. Advocacy | G8: Yes
B9: CAFEPADE | C9: Caisse des femmes paysannes pour le développement | D9: SHOW JUMPING | E9: Implementation | F9: MoU. Advocacy | G9: Yes
B10: CBFC | C10: Consortium Brave Femmes du Congo | D10: SHOW JUMPING | E10: Implementation | F10: MoU. Advocacy | G10: Yes
B11: SOCEARUCO | C11: Environmental and agrarian civil society of Congo | D11: Network CSO | E11: Designing, Planning, implementation and monitoring | F11: MoU. Advocacy | G11: Yes
B12: TRAFEED | C12: Networking with Federations of Women and Children in Need | D12: SHOW JUMPING | E12: Implementation | F12: MoU. Advocacy | G12: Yes
B13: CIAPAFED | D13: Society civil organization | E13: Planning & implementation | F13: Quarterly meetings, reporting, sharing action plans, (how we work with partners) | G13: Yes
B14: Mbou Mon Tour, | D14: Society civil organization | E14: implementation | G14: Yes
B15: Private companies - SOGENAC (cattle rearing) | D15: private sector | E15: Planning & implementation
B16: ERA Congo (carbon credit) | D16: private sector | E16: Learning
B17: SODEFOR (logging) | D17: private sector | E17: Learning
B18: Local communities managing CFCL | D18: Local communities | E18: implementation
B19: Academics and scientists monitoring peatlands and forests - University of Gembloux | D19: University | E19: Learning
B20: University of Kisangani, Univ Mbandaka | D20: University | E20: Learning
B21: Governorates | D21: Public sector | E21: Planning
B22: ICCN, | D22: Public sector | E22: Planning & implementation
B23: Provincial and territorial administrations | D23: Public sector | E23: Planning & implementation | F23: The provincial and territorial administration participates in the implementation of PIREDD project activities, and is involved in monitoring.
B24: RF Norway | D24: Society civil organization | E24: Learning
B25: ERAIFT | D25: Haute Ecole and Research | E25: Planning & implementation | F25: Involved in the planning and implementation of Alliance Verte, EU-Luki, PASAGAR and other projects
B26: ACODED/AMAR | D26: NGO | E26: implementation | F26: Stakeholder in the implementation of the Alliance Verte project
B27: ADEV | D27: NGO | E27: implementation | F27: Stakeholder in the implementation of the Alliance Verte project
B28: Caritas Matadi | D28: NGO | E28: implementation | F28: Stakeholder in the implementation of the Alliance Verte project
B29: CCPN | D29: NGO | E29: implementation | F29: Stakeholder in the implementation of the Alliance Verte project
B30: ULB-Coopération | D30: INGO | E30: Research & Development | F30: Implements research and development projects in the landscape
B31: UKV | D31: University | E31: Training and Research | F31: Stakeholder in the Alliance Verte project
B32: ISDR- Kinzau and ISEA-Tshela | D32: Universities | E32: Training and Research | F32: Stakeholder in the Alliance Verte project
B33: Provincial Government | D33: Public institution | E33: implementation | F33: Monitoring and evaluation of project implementation in the landscape
B34: Decentralized and centralized territorial entities | D34: Public institution | E34: Monitoring and evaluation | F34: Monitoring and evaluation of project implementation in the landscape
B35: CLP | D35: Public institution | E35: Planning | F35: Participates in project planning at the Luki Reserve
B36: CLDs | D36: Farmers' civil society | E36: Implementation | F36: Project beneficiaries in the landscape

Sheet Focus & Goals
B1: Conservation Focus | C1: Relevant OSP Goals | D1: Key Assumptions
A2: READ Me First | B2: Please list each conservation focus / focal interest. Biodiversity Focal Interests can be focal species or habitats/ ecological systems. Human Wellbeing Focal Interests can be those component of human wellbeing affected by the status of biodiversity focal interests (material and non-material benefits obtained by ecosystem. Please ensure that focus / focal interest is a subset of those selected under the OSP. You may define further detail. | C2: Based on the focus / focal interest selected, Please select the OSP Goal that your program is aiming to deliver. Please list the OSP Goal statement. | D2: Please identify the key assumptions that underpin the logical sequences linking strategies to one or more focal interests. Assumptions may also express how external variables may influence the achievement of results. Once the assumptions are identified, make sure to reflect them when completing the risk assessment.
A3: Example | B3: Coral Reef in Beta seascape. | C3: Live coral reef covers at least 25% of the reef within the priority coastal seascapes in country Y. | D3: WWF or its partner organization can monitor the live coral reef coverage in the coastal Beta seascape with proper funding.
B4: Elephants | C4: By 2035, the number of individual elephants in priority landscapes is stabilized compared to the 2026 baseline | D4: 1. No sudden environmental disturbances that could lead to mortality of elephants 2. Government policies remain in favour of endangered and protected species
B5: Bonobos | C5: By 2035, the number of Bonobos in targeted landscapes is stabilized compared to the 2026 baseline. | D5: 1. No sudden environmental disturbances that could lead to mortality of elephants 2. Government policies remain in favour of endangered and protected species
B6: Lowland Gorillas | C6: By 2035, the number of East lowland gorillas in targeted landscapes is stabilized compared to the 2024 baseline. | D6: 1. No sudden environmental disturbances that could lead to mortality of elephants 2. Government policies remain in favour of endangered and protected species
B7: Chimpanzees | C7: By 2035, the number of chimpanzees in targeted landscapes is stabilized compared to the 2024 baseline. | D7: 1. No sudden environmental disturbances that could lead to mortality of elephants 2. Government policies remain in favour of endangered and protected species
B8: Human Wellbeing | C8: By 2035, the wellbeing of targeted communities in targeted landscapes is improved by 20% relative to 2025 baseline. | D8: 1. No sudden environmental disturbances that could lead to mortality of elephants 2. Government policies remain in favour of endangered and protected species

Sheet Narrative TOC
B1: Read Me First | C1: Wildlife
A2: Narrative Theory of Change | B2: Please articulate the Theory of Change in Narrative. A Theory of Change (ToC) should be underpinned by evidence of the logic. Articulate the causal pathway that leads from the current to the desired situation, describing how the Programme activities will deliver the envisioned Programme Outputs and Outcomes, and ultimately the Programme/OSP Goals. Key risks associated with the key assumptions along the Theory of Change to achieve its Programme Outcomes and Goals must be articulated. A risk is potential future event that may impact achievement of goals. Assumptions are explicit statements of what the CO assumes is true. The logical sequences must link activities to one or more focal interests as reflected in a theory of change. Assumptions may also express how external variables may influence the achievement of results. Max. 500 words See Guidance by PPMS Step - Element 2.1 | C2: The DRC Wildlife Program aims to stabilize elephant populations and increase the populations of bonobos, chimpanzees, and lowland gorillas in priority landscapes by 2035. This will be achieved through a combination of strategies that reduce poaching and illegal wildlife trade, mitigate human-elephant conflict, and prevent zoonotic disease transmission. To address poaching and illegal capture, the program will promote alternative value chains that generate sustainable income for IPLCs who rely on wildlife as a source of livelihood. Increasing IPLC’s income from alternative sources will reduce the financial incentives for engaging in poaching and illegal wildlife trade. Complementing these efforts, awareness campaigns will be conducted to educate communities on the ecological and legal importance of protected species to shift social norms and discourage poaching and use of wildlife products. Additionally, WWF will support strengthening wildlife protection capacities through targeted initiatives such as training and providing monitoring and surveillance equipment. These efforts will be reinforced by enabling improved institutional collaboration among agencies with wildlife protection mandates, leading to more coordinated and effective monitoring, control, and prosecution to disrupt illegal wildlife trade networks and deter poaching. These efforts will contribute to stabilizing the population of the endangered species. Human-elephant conflict will be addressed through the Conflicts to Coexistence (C2C) approach. This strategy combines practical mitigation tools, behaviour change communication, and participatory planning with Indigenous Peoples and Local Communities (IPLCs). By enhancing the benefits of conservation and promoting shared decision-making, the program fosters more positive attitudes toward elephants. This shift in perception is expected to reduce retaliatory killings and promote coexistence, ultimately improving the well-being of communities and the conservation status of elephants. The program will implement targeted measures to mitigate zoonotic disease transmission due to increased human-wildlife interaction. These include pathogen monitoring, public health education, and habitat protection to reduce human-wildlife interactions. By framing wildlife conservation as a public health aspect, the program mobilizes broader support and contributes to reducing the risk of zoonotic spillover, particularly between humans and great apes. In parallel, the program will engage in targeted policy and advocacy efforts to create an enabling environment for forest conservation. A key focus area is facilitating and supporting cross-border cooperation to address the illegal timber trade, which contributes to habitat degradation. By working with national authorities, regional bodies, and international partners, the program aims to strengthen legal frameworks, harmonize enforcement protocols, and enhance information sharing across borders. These efforts are essential to curbing transboundary environmental crime, protecting critical habitats, and ensuring the long-term viability of both forest and wildlife resources in the region. These combined efforts are expected to reduce direct threats to wildlife, improve the management effectiveness of protected areas, and foster community stewardship. In doing so, the program contributes to the long-term conservation of key species and ecosystems, while also safeguarding human health and improving the livelihoods of targeted communities.
A3: Opportunities for Innovation | B3: Please articulate priority areas of innovation and research where needed. Innovation and Research activities must be included in the Programme Implementation Plan, Max. 500 words

Sheet Result Chain
B1: Conservation Focus of the Programme | C1: Priority Threats / Other Factors | D1: Result ID | E1: Program Outcomes | F1: Relevant Geographic Scope | G1: Relevant Thematic Scope | H1: Annual Result - Year 1 | I1: Output (Annual Result) - Year 2 | J1: Output (Annual Result) - Year 3 | K1: Output (Annual Result) - Year 4 | L1: Output (Annual Result) - Year 5 | M1: Key Assumptions & Risks | N1: Sustainability & Exit Plan
A2: READ Me First | B2: Please copy the list of Conservation Focus from the previous tab. | C2: For each Conservation Focus please list the priority threat (or other factors). Please use one line for each threat/factor. If a single threats affect more than one Conservation Focus, please list all the relevant conservation focus/focal interest under the column B. CMP Direct Threat Classification is available here - https://docs.google.com/spreadsheets/d/1rJSNz1LG_KOqoudVFglodx47HZ9LR-M6iVlRYMvn9Wk/edit#gid=310830663 Please ensure that priority threats/other factors are subset of those selected under the OSP. You may define further in detail. | E2: Please Describe the desired reduction of threats (or changes to the identified factors). Please make sure the statement is SMART. | F2: Please indicate the relevant Geographic Scope for each Outcome statement. Ensure to use one of the Geographic scope identified in the Scope tab of OSP Design Template. | G2: Please indicate the relevant Thematic Scope for each Goal statement. Ensure to use one of the Thematic scope identified in the Scope tab of OSP Design Template. | H2: Please define measurable Programme Annual Results which are milestones in achieving Programme outcomes. Therefore Programme Outcome must be embedded in the Programme Outputs. Outputs must represent tangible deliverables, within our area of control, that are critical to achieving the Programme Outcomes, in line with the Theory of Change. If there are areas of innovation and/or research, please make sure to include those outputs and activities as well. See the guidance on the approach to the Programme and Project Planning | M2: Please identify the key assumptions that underpin the logical sequences linking Outputs, and Outcomes, and to one or more Goals Assumptions may also express how external variables may influence the achievement of results. Once the assumptions are identified, make sure to reflect them when completing the risk assessment. WWF policies do not require risk assessment at program level but at Office level and at Project level. However each Program team is encouraged to perform Program Risk assessment. Use the Office risk register template in such case. | N2: Please describe how your program aims to ensure the sustainability of the program outcome and an eventual exit by WWF. See Guidance by PPMS Step - Element 2.3
A3: Example | B3: Coral Reef Marine priority species | C3: Overfishing / unsustainable fisheries | E3: By 2030, fisheries management plans are in place (implemented & monitored) in 80% of coastal fisheries in ABC coastal communities. | F3: Beta seascape | G3: Ocean | H3: Awareness of unsustainable fisheries increased in ABC coastal communities by 50% | I3: Technical capacity of 10 fisheries communities built on fisheries management plan | J3: 5 fisheries communities developed fisheries management plan | K3: 4 fisheries communities developed fisheries management plan | M3: Local communities can improve (or at least maintain) the economic state after the fisheries management plan. | N3: Creation of alternative sustainable income to ensure that the sustainable implementation of the fisheries management plan. Also, inclusion of CSO (and their capacity building) in the project implementation to enable the eventual exit of WWF and transition of responsibility to the local CSO.
F4: Beta seascape | G4: Ocean | H4: Baseline assessment of current fisheries practices conducted for 10 fisheries in ABC coastal community | K4: 50% of coastal fisheries are implementing and monitoring fisheries management plan | L4: 80% of coastal fisheries are implementing and monitoring fisheries management plan

Sheet Programme Implementation Plan
A1: Outcome name | B1: Outcome Name | C1: Results ID | D1: Output Statement | E1: FY26 Cost | F1: FY27 Cost | G1: FY28 Cost | H1: FY29 Cost | I1: FY30 Cost | J1: Total Output Cost + Management fee | K1: Current Project (CPM Project #) | L1: Target Funding Source
A2: =LEFT(C2,5) -> 1.1.1 | B2: =INDEX('Program M&E Plan'!$H$23:$H$40,MATCH('Programme Implementation Plan'!A2,'Program M&E Plan'!$G$23:$G$40,0)) -> Revenge killing of elephants reduced | C2: 1.1.1.1 | D2: By 2030, local communities and IPs living in and around the Salonga will be sensitized to the sustainable human-elephant coexistence.. | E2: 0 | F2: 50000 | G2: 50000 | H2: 50000 | I2: 50000 | J2: =SUM(E2:I2)*1.125 -> 225000 | K2: ABC224678
A3: =LEFT(C3,5) -> 1.1.2 | B3: =INDEX('Program M&E Plan'!$H$23:$H$40,MATCH('Programme Implementation Plan'!A3,'Program M&E Plan'!$G$23:$G$40,0)) -> Positive perception of HEC increased | C3: 1.1.2.1 | D3: By 2030, at least 1 study will be carried out on the perception of HEC in the Salonga landscape. | E3: 0 | F3: 20000 | G3: 0 | H3: 0 | I3: 20000 | J3: =SUM(E3:I3)*1.125 -> 45000 | K3: ABCC224678
A4: =LEFT(C4,5) -> 1.1.2 | B4: =INDEX('Program M&E Plan'!$H$23:$H$40,MATCH('Programme Implementation Plan'!A4,'Program M&E Plan'!$G$23:$G$40,0)) -> Positive perception of HEC increased | C4: 1.1.2.2 | D4: By 2030, participatory HEC dialogue forums are held annualy in 100% of high-conflict IPLC communities to co-design mitigation and coexistence solutions. | E4: 0 | F4: 5000 | G4: 5000 | H4: 5000 | I4: 5000 | J4: =SUM(E4:I4)*1.125 -> 22500
A5: =LEFT(C5,5) -> 1.1.2 | B5: =INDEX('Program M&E Plan'!$H$23:$H$40,MATCH('Programme Implementation Plan'!A5,'Program M&E Plan'!$G$23:$G$40,0)) -> Positive perception of HEC increased | C5: 1.1.2.3 | D5: By 2027, at least 50 HEC champions (including elders, women, and youth) are trained in conflict prevention, coexistence, and community outreach. | E5: 0 | F5: 5000 | G5: 5000 | H5: 5000 | I5: 5000 | J5: =SUM(E5:I5)*1.125 -> 22500
A6: =LEFT(C6,5) -> 1.1.3 | B6: Poaching reduced | C6: 1.1.3.1 | D6: By 2030, 100% of identified elephant hotspots or high-concentration areas are covered by patrols and biomonitoring surveys. | E6: 1600000 | F6: 1600000 | G6: 1600000 | H6: 1600000 | I6: 1600000 | J6: =SUM(E6:I6)*1.125 -> 9000000 | K6: ABCC224678
A7: =LEFT(C7,5) -> 1.1.3 | B7: Poaching reduced | C7: 1.1.3.2 | D7: By 2030, 100% of identified Bonobo hotspots or high-concentration areas are covered by community patrols & surveillance | E7: 350000 | F7: 350000 | G7: 350000 | H7: 350000 | I7: 350000 | J7: =SUM(E7:I7)*1.125 -> 1968750
A8: =LEFT(C8,5) -> 1.1.3 | B8: Poaching reduced | C8: 1.1.3.3 | D8: By 2030, 100% of identified lowland gorilla hotspots or high-concentration areas are covered by community patrols & surveillance | E8: 70000 | F8: 50000 | G8: 70000 | H8: 60000 | I8: 60000 | J8: =SUM(E8:I8)*1.125 -> 348750
A9: =LEFT(C9,5) -> 1.1.3 | B9: Poaching reduced | C9: 1.1.3.4 | D9: By 2030, 100% of identified Chimpanzee hotspots or high-concentration areas are covered by community patrols & surveillance | E9: 70000 | F9: 50000 | G9: 70000 | H9: 50000 | I9: 50000 | J9: =SUM(E9:I9)*1.125 -> 326250
A10: =LEFT(C10,5) -> 1.1.3 | B10: Poaching reduced | C10: 1.1.3.5 | D10: By 2030, Support the recruitment of new eco-guards in order to increase PNS staffing levels & their training and strengthening of operational capacities | E10: 250000 | F10: 250000 | G10: 250000 | H10: 250000 | I10: 250000 | J10: =SUM(E10:I10)*1.125 -> 1406250
A11: =LEFT(C11,5) -> 1.1.4 | B11: Trading of endangered species reduced | C11: 1.1.4.1 | D11: Support awareness-raising among law enforcement services on the trade in endangered species on Law No. 24/020 of December 30, 2024, amending and supplementing Law No. 14/003 of February 11, 2014 relating to nature conservation. | E11: 60000 | F11: 60000 | G11: 60000 | H11: 60000 | I11: 60000 | J11: =SUM(E11:I11)*1.125 -> 337500
A12: =LEFT(C12,5) -> 1.1.4 | B12: Trading of endangered species reduced | C12: 1.1.4.2 | D12: By 2028, at least 50% of law enforcement agencies dealing with endangered species in our landscapes are trained on endangered species protection | E12: 60000 | F12: 60000 | G12: 60000 | H12: 60000 | I12: 60000 | J12: =SUM(E12:I12)*1.125 -> 337500
A13: =LEFT(C13,5) -> 1.1.5 | B13: Management effectiveness Improved | C13: 1.1.5.1 | D13: By 2030, the assessment of management effectiveness using the IMET tool will be carried out at least annually at Salonga National Park and Luki Biosphere Reserve. | E13: 37000 | F13: 37000 | G13: 37000 | H13: 37000 | I13: 37000 | J13: =SUM(E13:I13)*1.125 -> 208125
A14: =LEFT(C14,5) -> 1.1.6 | B14: Zoonotic transmission reduced | C14: 1.1.6.1 | D14: By 2030, at least 50% of communication mechanisms and policies on zoonotic disease prevention and response are in place. | E14: 10000 | F14: 10000 | G14: 10000 | H14: 10000 | I14: 10000 | J14: =SUM(E14:I14)*1.125 -> 56250
A15: =LEFT(C15,5) -> 1.1.6 | B15: Zoonotic transmission reduced | C15: 1.1.6.2 | D15: By 2027, community health outreach and prevention communication campaigns on zoonoses are implemented in 100% of villages near great ape habitats. | E15: 44000 | F15: 40000 | G15: 40000 | H15: 40000 | I15: 40000 | J15: =SUM(E15:I15)*1.125 -> 229500
A16: =LEFT(C16,5) -> 4.1.1 | B16: =INDEX('Program M&E Plan'!$H$23:$H$40,MATCH('Programme Implementation Plan'!A16,'Program M&E Plan'!$G$23:$G$40,0)) -> Conservation related complaints reduced | C16: 4.1.1.1 | D16: By 2026, grievance redress mechanisms (GRMs) are established in 100% of target landscapes with annual tracking and response of cases. | E16: 400000 | F16: 400000 | G16: 400000 | H16: 400000 | I16: 400000 | J16: =SUM(E16:I16)*1.125 -> 2250000
A17: =LEFT(C17,5) -> 4.1.1 | B17: =INDEX('Program M&E Plan'!$H$23:$H$40,MATCH('Programme Implementation Plan'!A17,'Program M&E Plan'!$G$23:$G$40,0)) -> Conservation related complaints reduced | C17: 4.1.1.2 | D17: By 2030, the number of Human rights violations (physical and moral violations) linked to WWF's activities in priority landscapes are reduced | E17: 40000 | F17: 40000 | G17: 40000 | H17: 40000 | I17: 40000 | J17: =SUM(E17:I17)*1.125 -> 225000
A18: =LEFT(C18,5) -> 4.1.1 | B18: =INDEX('Program M&E Plan'!$H$23:$H$40,MATCH('Programme Implementation Plan'!A18,'Program M&E Plan'!$G$23:$G$40,0)) -> Conservation related complaints reduced | C18: 4.1.1.3 | D18: By 2030, at least 100% of ESSF flagship tools (ESIA, CGES, MGP, GBV Action Plan, Gender Analysis, HSSE Action Plan, Stakeholder Engagement Plan, and IP Engagement Plan) are developed, adopted, and implemented. | E18: 600000 | F18: 600000 | G18: 600000 | H18: 600000 | I18: 600000 | J18: =SUM(E18:I18)*1.125 -> 3375000
A19: =LEFT(C19,5) -> 4.1.1 | B19: =INDEX('Program M&E Plan'!$H$23:$H$40,MATCH('Programme Implementation Plan'!A19,'Program M&E Plan'!$G$23:$G$40,0)) -> Conservation related complaints reduced | C19: 4.1.1.4 | D19: By 2030, Salonga ecoguards are trained on human-right based approaches to law enforcement | E19: 200000 | F19: 200000 | G19: 200000 | H19: 200000 | I19: 200000 | J19: =SUM(E19:I19)*1.125 -> 1125000
A20: =LEFT(C20,5) -> 4.1.2 | B20: =INDEX('Program M&E Plan'!$H$23:$H$40,MATCH('Programme Implementation Plan'!A20,'Program M&E Plan'!$G$23:$G$40,0)) -> Positive perception on conservation improved | C20: 4.1.2.1 | D20: By 2020, studies or surveys on the negative perception of IPs/LCs living in the SNP and its periphery with regard to conservation are carried out. | E20: 0 | F20: 15000 | G20: 0 | H20: 0 | I20: 15000 | J20: =SUM(E20:I20)*1.125 -> 33750
A21: =LEFT(C21,5) -> 4.1.3 | B21: =INDEX('Program M&E Plan'!$H$23:$H$40,MATCH('Programme Implementation Plan'!A21,'Program M&E Plan'!$G$23:$G$40,0)) -> Students supported | C21: 4.1.3.1 | D21: By 2030, at least 5% of pupils in SNP (Monkoto & Yokelelu) will be supported through the provision of school supplies. | E21: 30000 | F21: 30000 | G21: 30000 | H21: 30000 | I21: 30000 | J21: =SUM(E21:I21)*1.125 -> 168750
A22: =LEFT(C22,5) -> 4.1.4 | B22: =INDEX('Program M&E Plan'!$H$23:$H$40,MATCH('Programme Implementation Plan'!A22,'Program M&E Plan'!$G$23:$G$40,0)) -> Household income increased | C22: 4.1.4.1 | D22: By 2030, at least 50% of households in targeted IP/LC communities are actively participating in at least one WWF-supported innovative income-generating activity (PES, biodiversity credits, LCFCs, or micro-enterprises). | E22: 60000 | F22: 60000 | G22: 60000 | H22: 60000 | I22: 60000 | J22: =SUM(E22:I22)*1.125 -> 337500
A23: =LEFT(C23,5) -> 4.1.4 | B23: =INDEX('Program M&E Plan'!$H$23:$H$40,MATCH('Programme Implementation Plan'!A23,'Program M&E Plan'!$G$23:$G$40,0)) -> Household income increased | C23: 4.1.4.2 | D23: By 2030, at least 36 structures are supported to implement Payment for Ecosystem Services (PES) schemes | E23: 400000 | F23: 400000 | G23: 400000 | H23: 400000 | I23: 400000 | J23: =SUM(E23:I23)*1.125 -> 2250000
A24: =LEFT(C24,5) -> 4.1.4 | B24: =INDEX('Program M&E Plan'!$H$23:$H$40,MATCH('Programme Implementation Plan'!A24,'Program M&E Plan'!$G$23:$G$40,0)) -> Household income increased | C24: 4.1.4.3 | D24: By 2030, WWF facilitates partnerships with at least 120 LCFCs, OECMs, and private sector entities to promote the delivery and sustainability of ecosystem services in target landscapes. | E24: 400000 | F24: 400000 | G24: 320000 | H24: 400000 | I24: 400000 | J24: =SUM(E24:I24)*1.125 -> 2160000
A25: =LEFT(C25,5) -> 4.1.4 | B25: =INDEX('Program M&E Plan'!$H$23:$H$40,MATCH('Programme Implementation Plan'!A25,'Program M&E Plan'!$G$23:$G$40,0)) -> Household income increased | C25: 4.1.4.4 | D25: By 2030, partnerships with Mobil Money operators to facilitate PSE transactions and other forms of credit is established | E25: 50000 | F25: 50000 | G25: 50000 | H25: 50000 | I25: 50000 | J25: =SUM(E25:I25)*1.125 -> 281250
A26: =LEFT(C26,5) -> 4.1.4 | B26: =INDEX('Program M&E Plan'!$H$23:$H$40,MATCH('Programme Implementation Plan'!A26,'Program M&E Plan'!$G$23:$G$40,0)) -> Household income increased | C26: 4.1.4.5 | D26: By 2030, at least 5 value chains (rice, charcoal, honey, etc.) are developed with market access in priority landscapes. | E26: 600000 | F26: 600000 | G26: 600000 | H26: 600000 | I26: 600000 | J26: =SUM(E26:I26)*1.125 -> 3375000
A27: =LEFT(C27,5) -> 4.1.5 | B27: =INDEX('Program M&E Plan'!$H$23:$H$40,MATCH('Programme Implementation Plan'!A27,'Program M&E Plan'!$G$23:$G$40,0)) -> Access to materials of good life improved | C27: 4.1.5.1 | D27: By 2030, at least 4 water points (e.g., boreholes, wells) are constructed or rehabilitated in underserved IPLC communities within WWF-supported landscapes. | E27: 0 | F27: 50000 | G27: 50000 | H27: 50000 | I27: 25000 | J27: =SUM(E27:I27)*1.125 -> 196875
... A37: =LEFT(C37,5) -> 4.1.7 | B37: =INDEX('Program M&E Plan'!$H$23:$H$40,MATCH('Programme Implementation Plan'!A37,'Program M&E Plan'!$G$23:$G$40,0)) -> #N/A | C37: 4.1.7.3 | D37: By 2030, at least USD 50 million will be mobilized internationally by the Congolese government (MEDD) to finance nature conservation and Climate Action with the support of WWF-DRC. | E37: 0 | F37: 34000 | G37: 20000 | H37: 10000 | I37: 0 | J37: =SUM(E37:I37)*1.125 -> 72000
E38: =SUM(E2:E37)*1.125 -> 7774875 | F38: =SUM(F2:F37)*1.125 -> 7713000 | G38: =SUM(G2:G37)*1.125 -> 7714125 | H38: =SUM(H2:H37)*1.125 -> 7714125 | I38: =SUM(I2:I37)*1.125 -> 7517250 | J38: =SUM(J2:J37) -> 38433375
E40: =SUM(E2:E34)*1.125 -> 7718625 | F40: =SUM(F2:F34)*1.125 -> 7618500 | G40: =SUM(G2:G34)*1.125 -> 7635375 | H40: =SUM(H2:H34)*1.125 -> 7646625 | I40: =SUM(I2:I34)*1.125 -> 7461000 | J40: =SUM(J2:J34)*1.125 -> 42840141

Sheet Program M&E Plan
A1: Programme M&E plan | B1: Program | C1: Prog_ID | D1: Relevant Geographic Scope | E1: Focus | F1: Priority Threats / Other Factors | G1: Result ID | H1: Result Name | I1: Goal, Outcome and Output Statement | J1: Indicator | K1: Description | L1: Means of Verification (Source of Data) | M1: Data Collection and Analysis Methodology | N1: Frequency of Measurement | O1: Key Assumptions & Risks | P1: Baseline | Q1: Year 1 Target | R1: Year 2 Target | S1: Year 3 Target | T1: Year 4 Target | U1: End-line Target | V1: Location | W1: Responsible
A2: OSP Goals | B2: Species Conservation | C2: 1 | E2: Species (Elephants) | F2: Poaching and Illegal capture | G2: 1.1 | H2: Elephant Species | I2: By 2035, the number of individual elephants in priority landscapes is stabilized compared to the 2026 baseline | J2: Number of individual elephants | K2: Population Size (N) | L2: Elephant Survey data | M2: Line transect distance sampling , Camera trap distance sampling, DNA Capture-Recapture | N2: Endline | O2: 1. No sudden environmental disturbances that could lead to mortality of elephants 2. Government policies remain in favour of endangered and protected species | P2: Salonga 1560 | U2: 1560 | V2: Salonga
J3: Number of elephants per surface area in sqkm | K3: Density (n/sqkm) | L3: Elephant Survey database | M3: Line transect distance sampling , Camera trap distance sampling, DNA Capture-Recapture | N3: Endline | P3: 0.18 | U3: 0.18
J4: Number of sightings of elephants in an area per unit of sampling distance in km | K4: Encounter rate (n/km) | L4: Elephant Survey database | M4: Line transect distance sampling , Reconnaissance survey | N4: Midline/endline | P4: TBD | Q4: TBD | S4: TBD | U4: TBD
J5: Proportion of area occupied by elephants in an area | K5: Occupancy rate (%) or Spatial distribution | L5: Elephant Survey database | M5: Line transect distance sampling , Camera trap occupancy | N5: Midline/endline | P5: TBD | Q5: TBD | S5: TBD | U5: TBD
J6: Number of independent detection events of elephants captured with camera traps per unit of sampling day | K6: Capture/Detection rate | L6: Elephant Survey database | M6: Camera trap occupancy, camera trap reconnaissance survey | N6: Midline/endline | P6: TBD | Q6: TBD | S6: TBD | U6: TBD
B7: Species Conservation | C7: 1 | E7: Species (Bonobos) | F7: poaching and Illegal capture | G7: 1.2 | H7: Bonobo Species | I7: By 2035, the number of Bonobos in targeted landscapes is increased compared to the 2026 baseline. | J7: Number of individual Bonobos | K7: Targeted Landscapes include Salonga & LTMN landscapes Population size (N) | L7: Great apes Survey Data (With validated analyses and report) | M7: Line Transect Distance Sampling, Camera Trap Distance Sampling, DNA Capture-Recapture | N7: Endline | O7: 1. No sudden environmental and/or zoonotic disturbances that could lead to mortality of Bonobos apes 2. Government policies remain in favour of endangered and protected species | P7: LTMN/Malebo: 4000 Salonga 12000 | U7: LTMN/Malebo: 4000 Salonga 12000
J8: Number of bonobos in an area per surface area | K8: Density (n/sqkm) | L8: Great apes Survey Data (With validated analyses and report) | M8: Line Transect Distance Sampling, Camera Trap Distance Sampling, DNA Capture-Recapture | N8: Endline | P8: LTMN/Malebo:0.739 Salonga 0.38 | U8: LTMN/Malebo:0.739 Salonga 0.38
J9: Number of sightings of Bonobos in an area per unit of sampling distance in km | K9: Encounter rate (n/km) | L9: Great apes Survey Data (With validated analyses and report) | M9: Line Transect Distance Sampling, Walk Reconnaissance Survey | N9: Midline/endline | P9: TBD | U9: TBD
J10: Proportion of surface area occupied by Bonobos in an area | K10: Occupancy rate (%) or Spatial distribution | L10: Great apes Survey Data (With validated analyses and report) | M10: Line Transect Distance Sampling, Camera Trap Occupancy | N10: Midline/endline | P10: TBD | U10: TBD
J11: Number of independent detection events of Bonobos captured with camera traps per unit of sampling day | K11: Capture rate (# independent events/day) | L11: Great apes Survey Data (With validated analyses and report) | M11: Camera Trap Occupancy, Camera Trap Reconnaissance survey | N11: Midline/endline | P11: TBD | U11: TBD
B12: Species Conservation | C12: 1 | E12: Species (Lowland Gorillas) | F12: poaching and Illegal capture | G12: 1.3 | H12: Lowland gorillas Species | I12: By 2035, the number of East lowland gorillas in targeted landscapes is stabilized compared to the 2024 baseline. | J12: Number of individual lowland gorillas | K12: Targeted Landscapes include Virunga-Itombwe landscape Population size (N) | L12: Great apes Survey Data (With validated analyses and report) | M12: Line Transect Distance Sampling, Camera Trap Distance Sampling, DNA Capture-Recapture | N12: Endline | O12: 1. No sudden environmental and/or zoonotic disturbances that could lead to mortality of lowland Gorillas 2. Government policies remain in favour of endangered and protected species | P12: TBD | U12: TBD
J13: Proportion of area occupied by lowland gorillas in an area | K13: Density (n/sqkm) | L13: Great apes Survey Data (With validated analyses and report) | M13: Line Transect Distance Sampling, Camera Trap Distance Sampling, DNA Capture-Recapture | N13: Endline | P13: TBD | U13: TBD
J14: Number of sightings of lowland gorillas in an area per unit of sampling distance in km | K14: Encounter rate (n/km) | L14: Great apes Survey Data (With validated analyses and report) | M14: Line Transect Distance Sampling, Walk Reconnaissance Survey | N14: Midline/endline | P14: TBD | U14: TBD
J15: Proportion of surface area occupied by lowland gorillas in an area | K15: Occupancy rate (%) or Spatial distribution | L15: Great apes Survey Data (With validated analyses and report) | M15: Line Transect Distance Sampling, Camera Trap Occupancy | N15: Midline/endline | P15: TBD | U15: TBD
J16: Number of independent detection events of lowland gorillas captured with camera traps per unit of sampling day | K16: Capture rate (# independent events/day) | L16: Great apes Survey Data (With validated analyses and report) | M16: Camera Trap Occupancy, Camera Trap Reconnaissance survey | N16: Midline/endline
B17: Species Conservation | C17: 1 | E17: Species (Chimpanzees) | F17: poaching and Illegal capture | G17: 1.4 | H17: chimpanzes Species | I17: By 2035, the number of chimpanzees in targeted landscapes is stabilized compared to the 2024 baseline. | J17: Number of individual chimpanzees | K17: Targeted Landscapes include LTMN & Mayombe-Mangrove Population size (N) | L17: Great apes Survey Data (With validated analyses and report) | M17: Line Transect Distance Sampling, Camera Trap Distance Sampling, DNA Capture-Recapture | N17: Endline | O17: 1. No sudden environmental and/or zoonotic disturbances that could lead to mortality of Chimpanzees 2. Government policies remain in favour of endangered and protected species | P17: Mayombe /Luki:30 Virunga:40 | U17: Luki:30 Virunga:80
J18: Proportion of area occupied by chimpanzees in an area | K18: Density (n/sqkm) | L18: Great apes Survey Data (With validated analyses and report) | M18: Line Transect Distance Sampling, Camera Trap Distance Sampling, DNA Capture-Recapture | N18: Endline | P18: TBD | U18: TBD
J19: Number of sightings of chimpanzees in an area per unit of sampling distance in km | K19: Encounter rate (n/km) | L19: Great apes Survey Data (With validated analyses and report) | M19: Line Transect Distance Sampling, Walk Reconnaissance Survey | N19: Midline/endline | P19: TBD | U19: TBD
J20: Proportion of surface area occupied by chimpanzees in an area | K20: Occupancy rate (%) or Spatial distribution | L20: Great apes Survey Data (With validated analyses and report) | M20: Line Transect Distance Sampling, Camera Trap Occupancy | N20: Midline/endline | P20: TBD | U20: TBD
J21: Number of independent detection events of Chimpanzees captured with camera traps per unit of sampling day | K21: Capture rate (# independent events/day) | L21: Great apes Survey Data (With validated analyses and report) | M21: Camera Trap Occupancy, Camera Trap Reconnaissance survey | N21: Midline/endline | P21: TBD | U21: TBD
B22: Cross Cutting | C22: 1 | E22: Human Wellbeing | G22: 4.1 | H22: Human well being | I22: By 2035, the wellbeing of targeted communities in targeted landscapes is improved by 20% relative to 2025 baseline. | J22: Wellbeing score | K22: Wellbeing includes materials for good life, social cohesion, rights, access to natural resources/5 categories of wellbeing | L22: Wellbeing survey data (with linked database) | M22: Socioeconomic survey related to wellbeing aspects supported. | N22: Endline | O22: There are no major conflicts, displacements, or political interference that would disrupt livelihoods, services, or community cohesion. | P22: LTMN : 0.3 Salonga : 0.52 Mayombe/Luki: Virunga/Itombwe | U22: LTMN : 0.35 Salonga : 0.55 Mayombe/Luki: Virunga/Itombwe
A23: Programme Outcomes | E23: Species (Elephants) | F23: Revenge Killing of Elephants from HEC | G23: 1.1.1 | H23: Revenge killing of elephants reduced | I23: By 2030, revenge killings of elephants in priority landscape are maintained to zero % | J23: % of HEC incidents that have resulted in revenge killings of elephants | K23: Will focus on the Salonga landscape Numerator: Number of HEC incidents that have resulted in 1 or more elephants being killed. | L23: HEC Database | M23: HEC Monitoring | N23: Annual | O23: Effective monitoring will allow timely reporting and redress of HEC to prevent retaliation (is this within our control) Fair and timely compensation (or alternatives like insurance schemes) exists for losses caused by elephants. The different authorities mandated to combat HEC will play their roles collaboratively | P23: Salonga 0% | Q23: 0 | R23: 0 | S23: 0 | T23: 0 | U23: 0
J24: Total number of elephants killed as a result of HEC revenge killings | K24: This will show the severity of retaliatory killings | L24: HEC Database | M24: HEC Monitoring | N24: Annual | P24: Salonga 0 | Q24: 0 | R24: 0 | S24: 0 | T24: 0 | U24: 0
E25: Species (Elephants) | F25: Lack of awareness and Knowledge on protected species | G25: 1.1.2 | H25: Positive perception of HEC increased | I25: By 2030, the positive perception of HEC by IP&LC in priority landscapes is improved by at least 25% compared to the baseline established in 2025 | J25: HEC perception score | K25: (in percentage) | L25: Perception survey data | M25: Perception survey | N25: Annual | O25: The people are willing to change their perception and behavior from retaliation to coexistence Local communities value elephant conservation because they see benefits such as revenue from ecotourism, or community conservation programs. | P25: TBD | Q25: TBD | R25: TBD | S25: TBD | T25: TBD | U25: TBD
J26: Number of reported complaints linked to HEC recorded each year | K26: Numerator: Number of complaints that are specifically linked to Human-Elephant Conflict (e.g., crop damage, property destruction, human injury/fatality caused by elephants). each year Denominator: Total number of complaints reported through the complaints mechanism or reporting system, regardless of the issue. | L26: Grievance mechanism database | M26: Grievance mechanism system | N26: Annually | P26: Salonga:5 | Q26: Salonga:5 | R26: Salonga:5 | S26: Salonga:5 | T26: Salonga:5 | U26: Salonga:5
E27: Species (Elephants, Bonobos, Lowland gorillas, Chimpanzees) | F27: Poaching and Illegal capture | G27: 1.1.3 1.2.1 1.3.1 1.4.1 | H27: Poaching reduced | I27: By 2030, the number of poaching signs per unit effort (n/km) in targeted landscapes is reduced by at least 20% relative to the 2024 baseline | J27: Number of poaching signs recorded per unit effort (n/km) | K27: The indicator measure the poaching encounter rate and relates all the focus species (Elephants, Great apes, duikers) because it would be difficult to relate some poaching signs to a species | L27: Species Survey Database (With validated analyses and report) | M27: Line Transect Distance Sampling, Camera Trap Distance Sampling, Walk Reconnaissance Survey | N27: Midline (only measured half way and at the end) | O27: Poaching laws are enforced by the relevant authorities There is resources and collaboration by the different authorities mandated to combat poaching | P27: LTMN : 0 Salonga : 0.00024 Mayombe/Luki :0 | Q27: LTMN : 0 Salonga : 0.0002 Mayombe/Luki:0 | R27: LTMN : 0 Salonga : 0.00015 Mayombe/Luki:0 | S27: LTMN : 0 Salonga : 0.00015 Mayombe/Luki:0 | T27: LTMN : 0 Sal : 0.0001 Mayombe/Luki:0 | U27: LTMN : 0 Sal : 0.0001 Mayombe/Luki:0
E28: Species (Elephants, Bonobos, Lowland gorillas, Chimpanzees) | F28: Poaching and Illegal capture | G28: 1.1.4 1.2.2 1.3.2 1.4.2 | H28: Trading of endangered species reduced | I28: The percentage of endangered species products recorded in markets or being trafficked compared to the total hunting products encountered is reduced by at least 30% compared to 2025. | J28: Percentage of hunting products recorded in markets or during trafficking that originate from endangered species | K28: Numerator: Number of hunting products encountered (in markets or in transit) that are identified as originating from endangered species Denominator: Total number of hunting products encountered in markets or in transit, regardless of species | L28: Market survey data Traffick Database | N28: Annual | O28: Poaching laws are enforced by the relevant authorities Stronger enforcement at border agencies preventing illegal products from passing through undetected. Awareness campaigns lead to behavior change and reduced demand for endangered species products Protein alternatives and local food systems improve, reducing reliance on hunting endangered species | P28: LTMN :TBD Sal : 8% Mayombe/Luki:0% | Q28: LTMN : Sal : 6% Mayombe/Luki:0% | R28: LTMN : Sal : 4% Mayombe/Luki:0% | S28: LTMN : Sal : 3% Mayombe/Luki:0% | T28: LTMN : Sal : 2% Mayombe/Luki:0% | U28: LTMN : Sal : 1% Mayombe/Luki:0%
E29: Species (Elephants, Bonobos, Lowland gorillas, Chimpanzees) | F29: Poor and/or weak governance, management, and capacities | G29: 1.1.5 1.2.3 1.3.3 1.4.3 | H29: Management effectiveness Improved | I29: By 2030, supported PAs have improved their management effectiveness by at least 10% compared to the 2025 baseline | J29: Management effectiveness score (by PA) | K29: https://rris.biopama.org/node/18795 | L29: IMET Scoring data | M29: IMET Scoring | N29: Midline | O29: PA staff apply the knowledge and skills gained from training in the management practices of PAs The result of IMET can be used for adaptive management. | P29: Mayombe/Luki:50.8 Salonga 63.03 | Q29: Mayombe/Luki: 51.8 Salonga 65 | R29: Mayombe/Luki:52.81 | S29: Mayombe/Luki: 53.85 Salonga 66.9 | T29: Mayombe/Luki:54.8 | U29: Mayombe/Luki: 55.88 Salonga 69.33
E30: Species (Elephants, Bonobos, Lowland gorillas, Chimpanzees) | F30: Zoonotic Diseases | G30: 1.1.6 1.2.4 1.3.4 1.4.4 | H30: Zoonotic transmission reduced | I30: By 2030, the transmission of zoonotic pathogens between human and wildlife is reduced by at least 80% compared to the 2025 baseline, with zero documented cases of zoonotic transmission between humans and great apes. | J30: Number of people affected by zoonotic diseases | K30: (folivirus, anthrax, monkey pox) | L30: Landscape Lab result database and reports | M30: Lab test analysis | N30: Annual | O30: Animal handlers practice biosafety practices, and have sufficient PPE Communities understand the risks of zoonotic transmission and shift behaviors around hunting, handling bushmeat or other animal related product that could cause transmission | P30: LTMN : TBD Sal : TBD Vir / Itombwe:TBD | Q30: LTMN : TBD Sal : TBD Vir / Itombwe:TBD | R30: LTMN : TBD Sal : TBD Vir / Itombwe:TBD | S30: LTMN : TBD Sal : TBD Vir / Itombwe:TBD | T30: LTMN : TBD Sal : TBD Vir / Itombwe:TBD | U30: LTMN : TBD Sal : TBD Vir / Itombwe:TBD
J31: Number of animals affected by zoonotic diseases | K31: (folivirus, anthrax, monkey pox) | L31: Landscape Lab result database and reports | M31: Lab test analysis | N31: Annual | P31: LTMN : TBD Sal : TBD Vir / Itombwe:0 | Q31: LTMN : TBD Sal : TBD Vir / Itombwe:0 | R31: LTMN : TBD Sal : TBD Vir / Itombwe:0 | S31: LTMN : TBD Sal : TBD Vir / Itombwe:0 | T31: LTMN : TBD Sal : TBD Vir / Itombwe:0 | U31: LTMN : TBD Sal : TBD Vir / Itombwe:0
J32: Number of confirmed zoonotic transmission cases between humans and great apes | K32: (monkey pox) | L32: Landscape Lab result database and reports | M32: Lab test analysis | N32: Annual | P32: TDB | Q32: TDB | R32: TDB | S32: TDB | T32: TDB | U32: TDB
B33: Cross Cutting | E33: Human Wellbeing | F33: Human rights abuse | G33: 4.1.1 | H33: Conservation related complaints reduced | I33: By 2030, the percentage of conservation related complaints related to CCO-supported conservation activities in target landscapes is reduced by at least 90%. | J33: % of conservation related complaints related to CCO conservation activities | K33: This will be measured on national level not on program level. Numerator: Number of conservation related complaints related to CCO conservation activities Divided by: Denominator: Number of conservation related complaints | L33: Grievance mechanism database | M33: Grievance mechanism system | N33: Annually | O33: There is confidence and trust in grievance redress mechanisms and are communities are using it to report | P33: LTMN : 100% (10 complaints) Salonga: 100% (78 complaints) Mayombe/Luki:0% Vir / Itombwe:TBD | Q33: LTMN : 100% Salonga : 60% Mayombe/Luki:0% Vir / Itombwe:TBD | R33: LTMN : 80% Sal : 50% Mayombe/Luki:0% Vir / Itombwe:TBD | S33: LTMN : 50% Sal : 40% Mayombe/Luki:TBD Vir / Itombwe:TBD | T33: LTMN : 30% Sal : 30% Mayombe/Luki:TBD Vir / Itombwe:TBD | U33: LTMN : 10% Sal : 20% Mayombe/Luki:TBD Vir / Itombwe:TBD
J34: Number of human rights violation cases by WWF's or implementing partners staff | L34: Grievance mechanism database | M34: Grievance mechanism system | N34: Annually | P34: Salonga:55 | Q34: Salonga:45 | R34: Salonga:35 | S34: Salonga:25 | T34: Salonga:15 | U34: Salonga:5
B35: Cross Cutting | E35: Human Wellbeing | F35: Weak support to conservation | G35: 4.1.2 | H35: Positive perception on conservation improved | I35: By 2030, at least 80% of targeted IPLCs in CCO-supported landscapes have a positive perception towards conservation projects/ideas. | J35: % of targeted IPLC who have a positive perception towards CCO-supported conservation projects/ ideas | K35: This will be measured on national level not on program level. | L35: Perception survey data | M35: Perception Survey | N35: Annually | O35: Conservation efforts produce tangible social or economic benefits for IPLCs (e.g., jobs, ecosystem services, access rights) | P35: LTMN : TBD Sal : 63% Mayombe/Luki:TBD Vir / Itombwe:TBD | Q35: LTMN : Sal : 63% Mayombe/Luki Vir / Itombwe | R35: LTMN : Sal : 65% Mayombe/Luki Vir / Itombwe | S35: LTMN : Sal : 70% Mayombe/Luki Vir / Itombwe | T35: LTMN : Sal : 75% Mayombe/Luki Vir / Itombwe | U35: LTMN : Sal : 80% Mayombe/Luki Vir / Itombwe
B36: Cross Cutting | E36: Human Wellbeing | F36: Poverty and lack of buy in to conservation | G36: 4.1.3 | H36: Students supported | I36: By 2030, at least 20% of supported students complete primary or secondary school education | J36: Number of students supported with school materials | L36: School Records | M36: School Records | N36: Annually | O36: Parents/guardians and communities value and support education—especially for girls and IPs No major disruptions (e.g., political instability, natural disasters, pandemics) impact schooling | P36: Salonga: 3567 | Q36: 4000 | R36: 4500 | S36: 5000 | T36: 5500 | U36: 6000
B37: Cross Cutting | E37: Human Wellbeing | F37: Poverty | G37: 4.1.4 | H37: Household income increased | I37: By 2030, targeted IPLC gain at least a 10% increase in household income from WWF-supported activities compared to the 2025 baseline | J37: Average household income of targeted IPLC | K37: Household income could be derived from IGA value chains, tourism, etc. | L37: Household survey data | M37: Household survey on WWF-supported activities | N37: Midline (only measured half way and at the end) | O37: Markets remain stable or grow for the products/services linked to WWF-supported activities Climate and environmental conditions do not severely disrupt production (e.g., droughts, disease, flooding) | P37: LTMN :TBD Sal :TBD Mayombe/Luki TBD Vir / Itombwe TBD
J38: Average total annual income gained by IPLC through direct employment in conservation related activities | K38: The income that is paid to IPLC directly from conservation activities | L38: HR salary data | M38: HR salary checks | N38: Annually | P38: LTMN :TBD Sal :TBD Mayombe/Luki TBD Vir / Itombwe TBD | Q38: TBD | R38: TBD | S38: TBD | T38: TBD | U38: TBD
B39: Cross Cutting | E39: Human Wellbeing | F39: Poverty | G39: 4.1.5 | H39: Access to materials of good life improved | I39: By 2030, the number of targeted IPLC communities in WWF-supported landscapes having access to materials of good life has increased by at least 50% relative to the 2025 baseline | J39: % of targeted IPLC communities in the WWF-supported landscapes that have access to materials of good life | K39: Access means the ability for the targeted group to make use of the materials. Materials of good life include portable water, health care, natural resources, food, education and traditional sites inside PAs. Communities refers to a group of people living in one village. Numerator: Number of targeted communities with access to the materials of a good life Divided by: Denominator: Number of targeted communities | L39: Community survey as well as program data (with linked database) | M39: Community surveys and program progress reports | N39: Annually | O39: Communities are not subjected to conflict, displacement, or governance instability that disrupt access to basic needs or services. | P39: Sal : 28000 | Q39: Sal : 33600 | R39: Sal : 39200 | S39: Sal :44800 | T39: Sal : 50400 | U39: Sal : 56000
B40: Cross Cutting | E40: Human Wellbeing | F40: Exclusion of IPLCs Inadequate or Weak policy on Protection of IPLC rights | G40: 4.1.6 | H40: policies & decisions promoting IPLC rights enacted | I40: By 2030, at least one new or revised policies or decisions promoting the rights and interests of IP&LC enacted with WWF support | J40: Number of new or revised policy or decisions promoting the rights and interests of IPLC enacted with WWF support | K40: policies include decrees or other circular decisions | L40: Policy and advocacy database (With validated analyses and report) | M40: Policy and advocacy activities | N40: Annually | O40: The government is willing to engage with WWF and partners (incl. IPLC) in the propositions, enacting and reviewing of the policies/ decisions | P40: LTMN :TBD Salonga Decret of CFCL : 17 Mayombe/Luki TBD Vir / Itombwe TBD | Q40: Salonga Decret of CFCL : 17 | R40: Salonga Decret of CFCL : 20 | S40: Salonga Decret of CFCL : 17 | T40: Salonga Decret of CFCL : 25 | U40: Salonga Decret of CFCL : 25
A41: Programme Outputs (High level) Refers to the non-negotiable outputs that are critical for the success of the programme, based on the Theory of Change | G41: 1.1.1.1 | I41: By 2030, local communities and IPs living in and around the Salonga will be sensitized to the sustainable human-elephant coexistence.. | J41: # of local Human Wildlife Conflict (HWC) management strategies developed and approved | P41: Salonga:0 | Q41: Salonga:1 | R41: Salonga:0 | S41: Salonga:0 | T41: Salonga:0 | U41: Salonga:0
G42: 1.1.2.1 | I42: By 2030, at least 1 study will be carried out on the perception of HEC in the Salonga landscape.. | J42: number of study reports on HEC perception umber of studies/Perception index | P42: Salonga:0 | Q42: Salonga:1 | R42: Salonga:1 | S42: Salonga:1 | T42: Salonga:1 | U42: Salonga:1
J43: HEC Perception index | P43: TBD | Q43: TBD | R43: TBD | S43: TBD | T43: TBD | U43: TBD
G44: 1.1.2.2 | I44: By 2030, participatory HEC dialogue forums are held annualy in 100% of high-conflict IPLC communities to co-design mitigation and coexistence solutions. | J44: Number of community dialogue forums held per year | P44: 1 | Q44: 1 | R44: 1 | S44: 1 | T44: 1 | U44: 1
J45: Number of community members taking part in HEC Community dialogue | P45: 8 | Q45: 15 | R45: 15 | S45: 15 | T45: 15 | U45: 15
G46: 1.1.2.3 | I46: By 2027, at least 50 HEC champions (including elders, women, and youth) are trained in conflict prevention, coexistence, and community outreach. | J46: Number of HEC champions active and conducting peer outreach | P46: TBD
G47: 1.1.3.1 | I47: By 2030, 100% of identified elephant hotspots or high-concentration areas are covered by patrols and biomonitoring surveys. | J47: Percent of elephant hotspots or high concentration areas covered by patrols or biomonitoring surveys | P47: Salonga:100% | Q47: Salonga:100% | R47: Salonga:100% | S47: Salonga:100% | T47: Salonga:100% | U47: Salonga:100%
G48: 1.1.3.2 | I48: By 2030, 100% of identified Bonobo hotspots or high-concentration areas are covered by community patrols & surveillance | J48: Percent of Bonobos hotspots or high concentration areas covered by community patrols | P48: LTMN : 20% Salonga : 100% | Q48: LTMN : 25% Salonga : 100% | R48: LTMN : 30% Salonga : 100% | S48: LTMN : 50% Salonga : 100% | T48: LTMN : 70% Salonga : 100% | U48: LTMN : 100% SalOnga : 100%
J49: Number of community members conducting patrols and surveillance in Bonobos hotspots or high concentration areas | P49: LTMN : 4 | Q49: LTMN : 5 | R49: LTMN : 6 | S49: LTMN : 7 | T49: LTMN : 8 | U49: TBD
G50: 1.1.3.3 | I50: By 2030, 100% of identified lowland gorilla hotspots or high-concentration areas are covered by community patrols & surveillance | J50: Percent of lowland gorilla hotspots or high concentration areas covered by community patrols | P50: TBD | Q50: TBD | R50: TBD | S50: TBD | T50: TBD | U50: TBD
J51: Number of community members conducting patrols and surveillance in lowland gorilla hotspots or high concentration areas | P51: TBD | Q51: TBD | R51: TBD | S51: TBD | T51: TBD | U51: TBD
G52: 1.1.3.4 | I52: By 2030, 100% of identified Chimpanzee hotspots or high-concentration areas are covered by community patrols & surveillance | J52: Percent of Chimpanzee hotspots or high concentration areas covered by community patrols | P52: TBD | Q52: TBD | R52: TBD | S52: TBD | T52: TBD | U52: TBD
J53: Number of community members conducting patrols and surveillance in Chimpanzee hotspots or high concentration areas | P53: TBD | Q53: TBD | R53: TBD | S53: TBD | T53: TBD | U53: TBD
G54: 1.1.3.5 | I54: By 2030, Support the recruitment of new eco-guards in order to increase PNS staffing levels & their training and strengthening of operational capacities | J54: Number of ecogurds recruited with WWF support | P54: Salonga 210 | Q54: Salonga 62 | R54: Salonga 0 | S54: Salonga 50 | T54: Salonga 30 | U54: Salonga 30
G55: 1.1.4.1 | I55: Support awareness-raising among law enforcement services on the trade in endangered species on Law No. 24/020 of December 30, 2024, amending and supplementing Law No. 14/003 of February 11, 2014 relating to nature conservation. | J55: Percent of target law enforcement agencies sensitized on Nature conservation laws | P55: LTMN : 40% Salonga : 60% | Q55: LTMN :50% Salonga : 70% | R55: LTMN : 60% Salonga : 80% | S55: LTMN : 70% Salonga : 90% | T55: LTMN : 80% Salonga :95% | U55: LTMN : 100% Salonga : 100%
J56: Number of law enforcement officers sensitized on Nature conservation laws | P56: LTMN : 102 Sal : 25 Mayombe/Luki: 60 | Q56: TBD | R56: TBD | S56: TBD | T56: TBD | U56: TBD
G57: 1.1.4.2 | I57: By 2028, at least 50% of law enforcement agencies dealing with endangered species in our landscapes are trained on endangered species protection | J57: Percent of target law enforcement agencies sensitized on endangered species protection | P57: TBD | Q57: TBD | R57: TBD | S57: TBD | T57: TBD | U57: TBD
J58: Number of law enforcement officers sensitized on endangered species protection | P58: LTMN : 102 Sal : 25 Mayombe/Luki: 60 | Q58: LTMN : 20 Sal : 5 Mayombe/Luki:15 | R58: LTMN : 20 Sal :5 Mayombe/Luki: 0 | S58: LTMN : 20 Sal : 5 Mayombe/Luki: 0 | T58: LTMN : 20 Sal :5 Mayombe/Luki: 0 | U58: LTMN : 20 Sal : 5 Mayombe/Luki:0
G59: 1.1.5.1 | I59: By 2030, the assessment of management effectiveness using the IMET tool will be carried out at least annually at Salonga National Park and Luki Biosphere Reserve. | J59: Number of management effectiveness assessments conducted annually | P59: Luki 2 Salonga 6 | Q59: Luki 1 Salonga 1 | R59: Luki 1 | S59: Luki 1 Salonga 1 | T59: Luki 1 | U59: Luki 1 Salonga 1
G60: 1.1.6.1 | I60: By 2030, at least 50% of communication mechanisms and policies on zoonotic disease prevention and response are in place. | J60: Percentage of policies reviewed and updated. | P60: LTMN/Malebo : 10% Salonga : 20% Mayombe/Luki: 30% | Q60: LTMN/Malebo : 20% Sal : 20% Mayombe/Luki: 35% | R60: LTMN/Malebo : 25% Sal : 30% Mayombe/Luki: 40% | S60: LTMN/Malebo : 27% Sal : 35% Mayombe/Luki: 45% | T60: LTMN/Malebo : 30% Sal : 40% Mayombe/Luki: 50% | U60: LTMN/Malebo : 10% Sal :50% Mayombe/Luki: 60%
G61: 1.1.6.2 | I61: By 2027, community health outreach and prevention communication campaigns on zoonoses are implemented in 100% of villages near great ape habitats. | J61: Number of community health outreach and campaigns on zoonotic diseases prevention conducted. | P61: LTMN/Malebo :4 Salonga : 1 Mayombe/Luki: 0 | Q61: LTMN/Malebo :1 Salonga : 1 Mayombe/Luki: 1 | R61: LTMN/Malebo :1 Salonga : 1 Mayombe/Luki: 1 | S61: LTMN/Malebo :1 Salonga : 1 Mayombe/Luki: 1 | T61: LTMN/Malebo :1 Salonga : 1 Mayombe/Luki: 1 | U61: LTMN/Malebo :1 Salonga : 1 Mayombe/Luki: 1
J62: Number of community members trained with outreach and campaigns on zoonotic disease awareness | P62: LTMN/Malebo :0 Salonga : 0 Mayombe/Luki: 0 | Q62: LTMN/Malebo :0 Salonga : 0 Mayombe/Luki: 0 | R62: LTMN/Malebo :0 Salonga : 0 Mayombe/Luki: 0 | S62: LTMN/Malebo :0 Salonga : 0 Mayombe/Luki: 0 | T62: LTMN/Malebo :0 Salonga : 0 Mayombe/Luki: 0 | U62: LTMN/Malebo :0 Salonga : 0 Mayombe/Luki: 0
G63: 4.1.1.1 | I63: By 2026, grievance redress mechanisms (GRMs) are established in 100% of target landscapes with annual tracking and response of cases. | J63: % landscapres with grievance Mechanisms in place | P63: LTMN/Plateau:100% Sal : 100% Mayombe/Luki: 60% Vir / Itombwe:100% | Q63: LTMN/Plateau:100% Sal : 100% Mayombe/Luki: 80% Vir / Itombwe:100% | R63: LTMN/Plateau:100% Sal : 100% Mayombe/Luki: 100% Vir / Itombwe:100% | S63: LTMN/Plateau:100% Sal : 100% Mayombe/Luki: 100% Vir / Itombwe:100% | T63: LTMN/Plateau:100% Sal : 100% Mayombe/Luki: 100% Vir / Itombwe:100% | U63: LTMN/Plateau:100% Sal : 100% Mayombe/Luki: 100% Vir / Itombwe:100%
J64: % of grievances resolved within agreed timelines | P64: LTMN/Malebo :100% Salonga : 70% Mayombe/Luki: 30% | Q64: LTMN/Malebo :100% Salonga : 80% Mayombe/Luki: 100% | R64: LTMN/Malebo :100% Salonga : 100% Mayombe/Luki: 100% | S64: LTMN/Malebo :100% Salonga : 100% Mayombe/Luki: 100% | T64: LTMN/Malebo :100% Salonga : 100% Mayombe/Luki: 100% | U64: LTMN/Malebo :100% Salonga : 100% Mayombe/Luki: 100%
G65: 4.1.1.2 | I65: By 2030, the number of Human rights violations (physical and moral violations) linked to WWF's activities in priority landscapes are reduced | J65: Number of reported human rights violations cases associated with WWF-supported activities | P65: Salonga:55 | Q65: Salonga:45 | R65: Salonga:35 | S65: Salonga:25 | T65: Salonga:15 | U65: Salonga:5
G66: 4.1.1.3 | I66: By 2030, at least 100% of ESSF flagship tools (ESIA, CGES, MGP, GBV Action Plan, Gender Analysis, HSSE Action Plan, Stakeholder Engagement Plan, and IP Engagement Plan) are developed, adopted, and implemented. | J66: % of landscapes that have implemented 80% of their ESSF actions | P66: LTMN: 70% Sal : 70% Mayombe/Luki: 40% Vir / Itombwe:70% | Q66: LTMN: 70% Sal : 70% Mayombe/Luki: 60% Vir / Itombwe:70% | R66: LTMN: 80% Sal : 80% Mayombe/Luki: 80% Vir / Itombwe:70% | S66: LTMN: 90% Sal : 90% Mayombe/Luki: 100% Vir / Itombwe:80% | T66: LTMN: 95% Sal : 95% Mayombe/Luki: 100% Vir / Itombwe:90% | U66: LTMN:100% Sal : 100% Mayombe/Luki: 100% Vir / Itombwe:100%
G67: 4.1.1.4 | I67: By 2030, Salonga ecoguards are trained on human-right based approaches to law enforcement | J67: Number of eco-guards trained in human rights-based approaches to law enforcement | P67: Sal : 210 Mayombe/Luki: 60 | Q67: Sal :62 Mayombe/Luki: 15 | R67: Sal : 0 Mayombe/Luki: 0 | S67: Sal : 50 Mayombe/Luki: 0 | T67: Sal : 30 Mayombe/Luki: 0 | U67: Sal :30 Mayombe/Luki: 0
J68: % of trained eco-guards who demonstrate knowledge of human rights-based approaches in law enforcement | P68: Salonga 80% | Q68: 0.82 | R68: 0.85 | S68: 0.9 | T68: 0.95 | U68: 1
G69: 4.1.2.1 | I69: By 2030, studies or surveys on the negative perception of IPs/LCs living in the SNP and its periphery with regard to conservation are carried out. | J69: Number of perception studies or surveys conducted | P69: TBD | Q69: TBD | R69: TBD | S69: TBD | T69: TBD | U69: TBD
G70: 4.1.3.1 | I70: By 2030, at least 5% of pupils in SNP (Monkoto & Yokelelu) will be supported through the provision of school supplies. | J70: Number of pupils provided with school supplies | P70: Salonga: 3567 | Q70: 4000 | R70: 4500 | S70: 5000 | T70: 5500 | U70: 6000
G71: 4.1.4.1 | I71: By 2030, at least 50% of households in targeted IP/LC communities are actively participating in at least one WWF-supported innovative income-generating activity (PES, biodiversity credits, LCFCs, or micro-enterprises). | J71: # of households in target communities participating in WWF projects supported sustainable income-generating or diversified income sources | P71: 28000 | Q71: 33600 | R71: 39200 | S71: 44800 | T71: 50400 | U71: 56000
G72: 4.1.4.2 | I72: By 2030, at least 36 structures are supported to implement Payment for Ecosystem Services (PES) schemes | J72: # of target structures supported to implement PES scheme | P72: LTMN :4 Mayombe/Luki:3 | Q72: LTMN : 3 Mayombe/Luki:0 | R72: LTMN :0 Mayombe/Luki:0 | S72: LTMN :0 Mayombe/Luki:0 | T72: LTMN :0 Mayombe/Luki:0 | U72: LTMN :0 Mayombe/Luki:0
G73: 4.1.4.3 | I73: By 2030, WWF facilitates partnerships with at least 120 LCFCs, OECMs, and private sector entities to promote the delivery and sustainability of ecosystem services in target landscapes. | J73: Number of partnership agreements signed or established | P73: LTMN :0 Mayombe/Luki:1 | Q73: LTMN :2 Mayombe/Luki:0 | R73: LTMN :1 Mayombe/Luki:0 | S73: LTMN :0 Mayombe/Luki:0 | T73: LTMN :0 Mayombe/Luki:0 | U73: LTMN :0 Mayombe/Luki:0
G74: 4.1.4.4 | I74: By 2030, partnerships with Mobil Money operators to facilitate PSE transactions and other forms of credit is established | J74: Number of partnerships entered with operators to facilitate funds transfer to community | P74: LTMN :1 Sal : 1 Mayombe/Luki: 1 Vir / Itombwe:1 | R74: LTMN :1 Sal : 1 Mayombe/Luki: 1 Vir / Itombwe:1 | U74: LTMN :1 Sal : 1 Mayombe/Luki: 1 Vir / Itombwe:1
J75: Number of people receiving funds from established operators | P75: LTMN : Salonga: Mayombe/Luki: Vir / Itombwe: | Q75: TBD | R75: TBD | S75: TBD | T75: TBD | U75: TBD
G76: 4.1.4.5 | I76: By 2030, at least 5 value chains (rice, charcoal, honey, etc.) are developed with market access in priority landscapes. | J76: Number of value chains developed | P76: LTMN :0 Sal : 1 Mayombe/Luki: 2 Vir / Itombwe:TBD | Q76: LTMN :0 Sal : 1 Mayombe/Luki: 1 Vir / Itombwe:TBD | R76: LTMN :2 Sal : 0 Mayombe/Luki: 0 Vir / Itombwe:TBD | S76: LTMN :1 Sal : 1 Mayombe/Luki: 0 Vir / Itombwe:TBD | T76: LTMN :1 Sal : 0 Mayombe/Luki: 1 Vir / Itombwe:TBD | U76: LTMN :1 Sal : 1 Mayombe/Luki: 0 Vir / Itombwe:TBD
G77: 4.1.5.1 | I77: By 2030, at least 4 water points (e.g., boreholes, wells) are constructed or rehabilitated in underserved IPLC communities within WWF-supported landscapes. | J77: Number of functional water sources constructed or rehabilitated | P77: Mayombe-Mangroves: 2 Salonga: 4 | Q77: Mayombe-Mangroves: 2 Salonga: 1 | R77: Mayombe-Mangroves: 1 Salonga: 1 | S77: Mayombe-Mangroves: 2 Salonga: 1 | T77: Mayombe-Mangroves: 1 Salonga: 1 | U77: Mayombe-Mangroves: 0 Salonga: 1
G78: 4.1.5.2 | I78: By 2030, livelihood support is provided to at least 5,000 IP&LC communities in priority landscapes | J78: % of targetet IP &LC households provided with livelihood support | P78: TBD | Q78: TBD | R78: TBD | S78: TBD | T78: TBD | U78: TBD
G79: 4.1.5.3 | I79: By 2030, at least 15 solar-powered lighting or energy systems are installed in schools, health centers, or public spaces in priority villages. | J79: Number of functional renewable energy installations | P79: LTMN :0 Salonga: 2 Mayombe/Luki: 0 | Q79: LTMN :0 Salonga: 2 Mayombe/Luki: 0 | R79: LTMN :0 Salonga: 2 Mayombe/Luki: 0 | S79: LTMN :0 Salonga: 2 Mayombe/Luki: 0 | T79: LTMN :0 Salonga: 2 Mayombe/Luki: 0 | U79: LTMN :0 Salonga: 2 Mayombe/Luki: 0
G80: 4.1.5.4 | I80: By 2030, all targeted IP&LC communities define their "priorities of good life" through a participatory assessment, + these are integrated into local development planning. | J80: % of targeted IP&LC communities in the WWF-supported landscapes that have access to materials of good life | P80: LTMN : Salonga: 28000 Mayombe/Luki: 0 | Q80: LTMN : Salonga: 33600 Mayombe/Luki: 0 | R80: LTMN : Salonga: 39200 Mayombe/Luki: 0 | S80: LTMN : Salonga: 44800 Mayombe/Luki: 0 | T80: LTMN : Salonga: 50400 Mayombe/Luki: 0 | U80: LTMN : Salonga: 56000 Mayombe/Luki: 0
G81: 4.1.6.1 | I81: By 2030, at least 50% of decisions taken by protected area managers will take into account the interests of IPs/LCs in accessing resources. | J81: % of documented PA decisions (e.g., access rules, zoning, benefit-sharing) that include IPLC consultation records | P81: Salonga 20% | Q81: 0.25 | R81: 0.3 | S81: 0.35 | T81: 0.4 | U81: 0.5
G82: 4.1.6.2 | I82: By 2030, Support the analysis of legal texts relating to access to natural resources by communities in priority landscapes | J82: Number of policy/legal analysis reports completed and shared with decision-makers | P82: 0 | Q82: 1 | R82: 1 | S82: 1 | U82: 3
G83: 4.1.6.3 | I83: By2030, support the organization of three multi-stakeholder consultation meetings of representatives of government, civil society and indigenous peoples and local communities to advocate for policy reforms that include indigenous peoples and local communities. | J83: Number of stakeholder meetings convened with documented participation from IPLCs | P83: 0 | Q83: 0 | R83: 1 | S83: 2 | U83: 3
G84: 4.1.6.4 | I84: By 2030, provide technical support for the development, revision or validation of at least one draft policy, decree or strategy that explicitly protects the rights of indigenous peoples and local communities and their access to natural resources. | J84: Number of policy drafts/revisions with WWF-supported IPLC language or provisions | P84: 0 | R84: 1 | U84: 1
G85: 4.1.7.1 | I85: By 2030, representatives from WWF-supported landscapes in DRC participate in cross-border steering committee meetings on biodiversity and environmental governance, with documented contributions. | J85: % of cross-border meetings attended by WWF-supported landscape representatives | P85: Virunga: 0% | Q85: 0.1 | R85: 0.3 | S85: 0.5 | T85: 0.7 | U85: 1
G86: 4.1.7.2 | I86: By 2030, WWF provides technical, financial, or coordination support to the implementation of at least 6 national and international biodiversity-related strategies or frameworks (e.g., NBSAP, NDC, 30x30), including documented actions and results. | J86: Number of biodiversity-related national/international frameworks receiving documented WWF implementation support | P86: TBD | Q86: TBD | R86: TBD | S86: TBD | T86: TBD | U86: TBD
G87: 4.1.7.3 | I87: By 2030, at least USD 50 million will be mobilized internationally by the Congolese government (MEDD) to finance nature conservation and Climate Action with the support of WWF-DRC. | J87: Total USD committed to DRC for nature conservation and climate action (with WWF support) | P87: 0 | Q87: 0 | R87: 20 | S87: 20 | T87: 10 | U87: 50

Sheet Learning Questions
B1: Learning Questions
A2: READ Me First | B2: Please articulate specific learning questions that your program will regularly reflect on for the learning priority. Max 100 words.
A3: Example | B3: - To what extent are the program's activities effective in achieving the planned results? - What worked and what didn’t? - Were there any unintended consequences? (positive or negative/ internal or external) - Were there any emergent results? (more than the planned results)
